bluewave/__init__.py
bluewave/compare_pdfs.py
bluewave/compare_pdfs_go.py
bluewave/pdf_to_img.py
bluewave/pdf_to_img_go.py
bluewave/result_json_to_training_csv.py
bluewave/show_similarity_rectangles.py
bluewave/src/__init__.py
bluewave/src/aws_client.py
bluewave/src/compare_pdfs_text.py
bluewave/src/digit_tests.py
bluewave/src/find_common_substrings.py
bluewave/src/get_file_data.py
bluewave/src/importance_score.py
bluewave/src/pdf_duplicate_pages.py
bluewave/src/run_and_store_cross_pairs.py
bluewave/src/run_and_store_cross_pairs_go.py
bluewave/src/train_result_classifiers.py
bluewave/src/train_result_classifiers_go.py
bluewave/src/utils.py
bluewave-0.0.8.dist-info/LICENSE
bluewave-0.0.8.dist-info/METADATA
bluewave-0.0.8.dist-info/WHEEL
bluewave-0.0.8.dist-info/top_level.txt
bluewave-0.0.8.dist-info/RECORD
