Metadata-Version: 2.1
Name: bluewave
Version: 0.0.8
Summary: Python script to analyze the similarity of two PDFs
Author-email: bballboy8 <author@example.com>
Project-URL: Homepage, https://github.com/bballboy8/bluewave/
Project-URL: Bug Tracker, https://github.com/bballboy8/bluewave/issues
Classifier: Programming Language :: Python :: 3
Classifier: License :: OSI Approved :: MIT License
Classifier: Operating System :: OS Independent
Requires-Python: >=3.6
License-File: LICENSE
Requires-Dist: black (==22.10.0)
Requires-Dist: boto3 (==1.26.59)
Requires-Dist: matplotlib (==3.6.2)
Requires-Dist: numpy (==1.23.5)
Requires-Dist: pandas (==1.5.2)
Requires-Dist: Pillow (==9.3.0)
Requires-Dist: pre-commit (==2.20.0)
Requires-Dist: psycopg2 (==2.9.5)
Requires-Dist: pydivsufsort (==0.0.6)
Requires-Dist: PyMuPDF (==1.21.0)
Requires-Dist: pytest (==7.2.0)
Requires-Dist: scikit-learn (==1.1.3)
